{
  "name": "ZeroAI-UI Design Tokens",
  "version": "5.1.0",
  "description": "Framework-agnostic design tokens for AI-Native products - Taobao Orange Theme",
  "colors": {
    "human": {
      "primary": "#737373",
      "primary-light": "#A3A3A3",
      "primary-dark": "#525252",
      "surface": "#FFFFFF",
      "surface-elevated": "#FAFAFA",
      "surface-sunken": "#F5F5F5",
      "border": "#E5E5E5",
      "border-strong": "#D4D4D4",
      "text-primary": "#171717",
      "text-secondary": "#737373",
      "text-tertiary": "#A3A3A3",
      "note": "Neutral gray colors - low-key, non-distracting"
    },
    "ai": {
      "primary": "#FF6600",
      "primary-light": "#FF7A1F",
      "primary-dark": "#E55A00",
      "surface": "#FFF7F0",
      "surface-elevated": "#FFEDE0",
      "border": "rgba(255, 102, 0, 0.2)",
      "border-strong": "rgba(255, 102, 0, 0.4)",
      "note": "Taobao Orange - vibrant, energetic, warm"
    },
    "collaboration": {
      "primary": "#FF8533",
      "border": "rgba(255, 133, 51, 0.4)",
      "note": "Light variant of Taobao Orange for collaborative actions"
    },
    "semantic": {
      "success": "#10B981",
      "warning": "#F59E0B",
      "error": "#EF4444",
      "info": "#737373"
    }
  },
  "spacing": {
    "xs": "4px",
    "sm": "8px",
    "md": "16px",
    "lg": "24px",
    "xl": "32px",
    "2xl": "48px",
    "3xl": "64px",
    "mobile": {
      "xs": "3px",
      "sm": "6px",
      "md": "12px",
      "lg": "18px",
      "xl": "24px",
      "2xl": "36px",
      "note": "Mobile spacing is 0.75x of desktop"
    }
  },
  "typography": {
    "fontFamily": {
      "base": "-apple-system, BlinkMacSystemFont, 'Segoe UI', 'Roboto', 'Helvetica Neue', sans-serif",
      "ai": "'Nunito', -apple-system, BlinkMacSystemFont, sans-serif",
      "mono": "'SF Mono', 'Monaco', 'Inconsolata', 'Fira Code', monospace"
    },
    "fontSize": {
      "xs": "12px",
      "sm": "14px",
      "base": "16px",
      "lg": "18px",
      "xl": "20px",
      "2xl": "24px",
      "3xl": "30px",
      "4xl": "36px",
      "mobile": {
        "base": "14px",
        "note": "Mobile base font size is 14px (vs 16px on desktop)"
      }
    },
    "fontWeight": {
      "normal": "400",
      "medium": "500",
      "semibold": "600",
      "bold": "700"
    },
    "lineHeight": {
      "tight": "1.25",
      "normal": "1.5",
      "relaxed": "1.75"
    }
  },
  "borderRadius": {
    "none": "0",
    "sm": "4px",
    "md": "8px",
    "lg": "12px",
    "xl": "16px",
    "2xl": "24px",
    "full": "9999px"
  },
  "shadows": {
    "xs": "0 1px 2px rgba(0, 0, 0, 0.05)",
    "sm": "0 2px 4px rgba(0, 0, 0, 0.06)",
    "md": "0 4px 6px rgba(0, 0, 0, 0.08)",
    "lg": "0 10px 15px rgba(0, 0, 0, 0.1)",
    "xl": "0 20px 25px rgba(0, 0, 0, 0.12)",
    "2xl": "0 25px 50px rgba(0, 0, 0, 0.2)"
  },
  "breakpoints": {
    "xs": "0px",
    "sm": "640px",
    "md": "768px",
    "lg": "1024px",
    "xl": "1280px",
    "2xl": "1536px"
  },
  "mobile": {
    "touchTarget": {
      "min": "48px",
      "comfortable": "56px",
      "spacious": "64px"
    },
    "safeArea": {
      "top": "env(safe-area-inset-top)",
      "bottom": "env(safe-area-inset-bottom)",
      "left": "env(safe-area-inset-left)",
      "right": "env(safe-area-inset-right)"
    }
  },
  "animation": {
    "duration": {
      "fast": "150ms",
      "base": "300ms",
      "slow": "500ms"
    },
    "easing": {
      "standard": "cubic-bezier(0.4, 0, 0.2, 1)",
      "enter": "cubic-bezier(0, 0, 0.2, 1)",
      "exit": "cubic-bezier(0.4, 0, 1, 1)"
    }
  }
}
